{
  "galaxy_stats": {
    "missionsWon": 107751367,
    "missionsLost": 11448963,
    "missionTime": 103922854615,
    "bugKills": 8339904791,
    "automatonKills": 2703119046,
    "illuminateKills": 28,
    "bulletsFired": 70686057536,
    "bulletsHit": 70101641051,
    "timePlayed": 103922854615,
    "deaths": 369958908,
    "revives": 2,
    "friendlies": 51376790,
    "missionSuccessRate": 90,
    "accurracy": 99
  },
  "planets_stats": [
    {
      "planetIndex": 0,
      "missionsWon": 35840,
      "missionsLost": 4331,
      "missionTime": 668,
      "bugKills": 0,
      "automatonKills": 0,
      "illuminateKills": 16,
      "bulletsFired": 464,
      "bulletsHit": 316,
      "timePlayed": 668,
      "deaths": 6,
      "revives": 0,
      "friendlies": 0,
      "missionSuccessRate": 89,
      "accurracy": 68
    },
    {
      "planetIndex": 34,
      "missionsWon": 8960096,
      "missionsLost": 1185606,
      "missionTime": 7683624902,
      "bugKills": 859227646,
      "automatonKills": 118,
      "illuminateKills": 0,
      "bulletsFired": 5419666570,
      "bulletsHit": 6283473090,
      "timePlayed": 7683624902,
      "deaths": 31003873,
      "revives": 0,
      "friendlies": 4393489,
      "missionSuccessRate": 88,
      "accurracy": 100
    },
    {
      "planetIndex": 64,
      "missionsWon": 3312816,
      "missionsLost": 380102,
      "missionTime": 4031535690,
      "bugKills": 538441731,
      "automatonKills": 16718,
      "illuminateKills": 0,
      "bulletsFired": 3388303102,
      "bulletsHit": 3732657905,
      "timePlayed": 4031535690,
      "deaths": 14432249,
      "revives": 0,
      "friendlies": 2448070,
      "missionSuccessRate": 89,
      "accurracy": 100
    },
    {
      "planetIndex": 77,
      "missionsWon": 354,
      "missionsLost": 133,
      "missionTime": 223923,
      "bugKills": 26434,
      "automatonKills": 0,
      "illuminateKills": 0,
      "bulletsFired": 180939,
      "bulletsHit": 215782,
      "timePlayed": 223923,
      "deaths": 1263,
      "revives": 0,
      "friendlies": 62,
      "missionSuccessRate": 72,
      "accurracy": 100
    },
    {
      "planetIndex": 78,
      "missionsWon": 9145189,
      "missionsLost": 866313,
      "missionTime": 8336765295,
      "bugKills": 1016258836,
      "automatonKills": 348,
      "illuminateKills": 0,
      "bulletsFired": 6298402586,
      "bulletsHit": 7368924682,
      "timePlayed": 8336765295,
      "deaths": 27885194,
      "revives": 0,
      "friendlies": 4380768,
      "missionSuccessRate": 91,
      "accurracy": 100
    },
    {
      "planetIndex": 79,
      "missionsWon": 1346821,
      "missionsLost": 156140,
      "missionTime": 1000953216,
      "bugKills": 151404589,
      "automatonKills": 23,
      "illuminateKills": 0,
      "bulletsFired": 905425400,
      "bulletsHit": 1016021718,
      "timePlayed": 1000953216,
      "deaths": 3447276,
      "revives": 2,
      "friendlies": 679977,
      "missionSuccessRate": 89,
      "accurracy": 100
    },
    {
      "planetIndex": 80,
      "missionsWon": 3281,
      "missionsLost": 1378,
      "missionTime": 2178021,
      "bugKills": 256982,
      "automatonKills": 0,
      "illuminateKills": 0,
      "bulletsFired": 1652094,
      "bulletsHit": 1979435,
      "timePlayed": 2178021,
      "deaths": 13511,
      "revives": 0,
      "friendlies": 824,
      "missionSuccessRate": 70,
      "accurracy": 100
    },
    {
      "planetIndex": 107,
      "missionsWon": 8524,
      "missionsLost": 996,
      "missionTime": 7821725,
      "bugKills": 0,
      "automatonKills": 536627,
      "illuminateKills": 0,
      "bulletsFired": 3471082,
      "bulletsHit": 2007154,
      "timePlayed": 7821725,
      "deaths": 26238,
      "revives": 0,
      "friendlies": 2689,
      "missionSuccessRate": 89,
      "accurracy": 57
    },
    {
      "planetIndex": 125,
      "missionsWon": 5417853,
      "missionsLost": 343500,
      "missionTime": 6981024864,
      "bugKills": 808899978,
      "automatonKills": 93142,
      "illuminateKills": 0,
      "bulletsFired": 4998889509,
      "bulletsHit": 3084082475,
      "timePlayed": 6981024864,
      "deaths": 14397469,
      "revives": 0,
      "friendlies": 2384302,
      "missionSuccessRate": 94,
      "accurracy": 61
    },
    {
      "planetIndex": 126,
      "missionsWon": 9698390,
      "missionsLost": 624918,
      "missionTime": 11774609197,
      "bugKills": 1366929965,
      "automatonKills": 52464,
      "illuminateKills": 0,
      "bulletsFired": 8372522285,
      "bulletsHit": 5938168986,
      "timePlayed": 11774609197,
      "deaths": 28633152,
      "revives": 0,
      "friendlies": 5167047,
      "missionSuccessRate": 93,
      "accurracy": 70
    },
    {
      "planetIndex": 127,
      "missionsWon": 124011,
      "missionsLost": 28070,
      "missionTime": 41160733,
      "bugKills": 5116155,
      "automatonKills": 75,
      "illuminateKills": 0,
      "bulletsFired": 32721959,
      "bulletsHit": 30951778,
      "timePlayed": 41160733,
      "deaths": 182000,
      "revives": 0,
      "friendlies": 13325,
      "missionSuccessRate": 81,
      "accurracy": 94
    },
    {
      "planetIndex": 152,
      "missionsWon": 1439751,
      "missionsLost": 116155,
      "missionTime": 1985128490,
      "bugKills": 24618,
      "automatonKills": 134608396,
      "illuminateKills": 0,
      "bulletsFired": 1016387797,
      "bulletsHit": 635676891,
      "timePlayed": 1985128490,
      "deaths": 5445673,
      "revives": 0,
      "friendlies": 592375,
      "missionSuccessRate": 92,
      "accurracy": 62
    },
    {
      "planetIndex": 153,
      "missionsWon": 5284537,
      "missionsLost": 655345,
      "missionTime": 4385581048,
      "bugKills": 519,
      "automatonKills": 342135313,
      "illuminateKills": 0,
      "bulletsFired": 2476317107,
      "bulletsHit": 2436786038,
      "timePlayed": 4385581048,
      "deaths": 21448054,
      "revives": 0,
      "friendlies": 2101307,
      "missionSuccessRate": 88,
      "accurracy": 98
    },
    {
      "planetIndex": 154,
      "missionsWon": 1369091,
      "missionsLost": 21782,
      "missionTime": 751310354,
      "bugKills": 1184,
      "automatonKills": 57851203,
      "illuminateKills": 0,
      "bulletsFired": 307245900,
      "bulletsHit": 160791455,
      "timePlayed": 751310354,
      "deaths": 2048958,
      "revives": 0,
      "friendlies": 358100,
      "missionSuccessRate": 98,
      "accurracy": 52
    },
    {
      "planetIndex": 155,
      "missionsWon": 4501,
      "missionsLost": 1191,
      "missionTime": 3065143,
      "bugKills": 0,
      "automatonKills": 271485,
      "illuminateKills": 0,
      "bulletsFired": 1777198,
      "bulletsHit": 1292161,
      "timePlayed": 3065143,
      "deaths": 14876,
      "revives": 0,
      "friendlies": 1445,
      "missionSuccessRate": 79,
      "accurracy": 72
    },
    {
      "planetIndex": 168,
      "missionsWon": 3148452,
      "missionsLost": 377829,
      "missionTime": 3693059797,
      "bugKills": 503799118,
      "automatonKills": 0,
      "illuminateKills": 0,
      "bulletsFired": 3027005605,
      "bulletsHit": 3527063919,
      "timePlayed": 3693059797,
      "deaths": 13527878,
      "revives": 0,
      "friendlies": 2380700,
      "missionSuccessRate": 89,
      "accurracy": 100
    },
    {
      "planetIndex": 169,
      "missionsWon": 10957971,
      "missionsLost": 1166667,
      "missionTime": 8427046648,
      "bugKills": 1147244761,
      "automatonKills": 455,
      "illuminateKills": 0,
      "bulletsFired": 6772752107,
      "bulletsHit": 7772567224,
      "timePlayed": 8427046648,
      "deaths": 30941693,
      "revives": 0,
      "friendlies": 5330627,
      "missionSuccessRate": 90,
      "accurracy": 100
    },
    {
      "planetIndex": 170,
      "missionsWon": 7192761,
      "missionsLost": 780411,
      "missionTime": 6967833272,
      "bugKills": 853712345,
      "automatonKills": 144,
      "illuminateKills": 0,
      "bulletsFired": 5318272232,
      "bulletsHit": 6189683818,
      "timePlayed": 6967833272,
      "deaths": 24152591,
      "revives": 0,
      "friendlies": 3761261,
      "missionSuccessRate": 90,
      "accurracy": 100
    },
    {
      "planetIndex": 195,
      "missionsWon": 344255,
      "missionsLost": 33318,
      "missionTime": 1075254911,
      "bugKills": 0,
      "automatonKills": 72405513,
      "illuminateKills": 0,
      "bulletsFired": 543769696,
      "bulletsHit": 558228918,
      "timePlayed": 1075254911,
      "deaths": 2808749,
      "revives": 0,
      "friendlies": 229595,
      "missionSuccessRate": 91,
      "accurracy": 100
    },
    {
      "planetIndex": 196,
      "missionsWon": 5099887,
      "missionsLost": 689538,
      "missionTime": 5273890662,
      "bugKills": 597,
      "automatonKills": 372670692,
      "illuminateKills": 0,
      "bulletsFired": 2740311446,
      "bulletsHit": 2728064524,
      "timePlayed": 5273890662,
      "deaths": 24848035,
      "revives": 0,
      "friendlies": 2353741,
      "missionSuccessRate": 88,
      "accurracy": 99
    },
    {
      "planetIndex": 197,
      "missionsWon": 3860858,
      "missionsLost": 386599,
      "missionTime": 2975079625,
      "bugKills": 24729,
      "automatonKills": 230715560,
      "illuminateKills": 0,
      "bulletsFired": 1609866217,
      "bulletsHit": 1212233744,
      "timePlayed": 2975079625,
      "deaths": 12047585,
      "revives": 0,
      "friendlies": 1471319,
      "missionSuccessRate": 90,
      "accurracy": 75
    },
    {
      "planetIndex": 211,
      "missionsWon": 2328179,
      "missionsLost": 253678,
      "missionTime": 1854919255,
      "bugKills": 211534942,
      "automatonKills": 126,
      "illuminateKills": 0,
      "bulletsFired": 1354594414,
      "bulletsHit": 1572678476,
      "timePlayed": 1854919255,
      "deaths": 7614955,
      "revives": 0,
      "friendlies": 1081899,
      "missionSuccessRate": 90,
      "accurracy": 100
    },
    {
      "planetIndex": 212,
      "missionsWon": 8038685,
      "missionsLost": 906995,
      "missionTime": 6422744119,
      "bugKills": 812260020,
      "automatonKills": 133,
      "illuminateKills": 0,
      "bulletsFired": 5166443424,
      "bulletsHit": 5955835984,
      "timePlayed": 6422744119,
      "deaths": 24817736,
      "revives": 0,
      "friendlies": 3964682,
      "missionSuccessRate": 89,
      "accurracy": 100
    },
    {
      "planetIndex": 238,
      "missionsWon": 2075699,
      "missionsLost": 151905,
      "missionTime": 3262271460,
      "bugKills": 19998,
      "automatonKills": 213035624,
      "illuminateKills": 0,
      "bulletsFired": 1614231260,
      "bulletsHit": 1326700222,
      "timePlayed": 3262271460,
      "deaths": 9648071,
      "revives": 0,
      "friendlies": 943015,
      "missionSuccessRate": 93,
      "accurracy": 82
    },
    {
      "planetIndex": 239,
      "missionsWon": 4198,
      "missionsLost": 1609,
      "missionTime": 2583832,
      "bugKills": 0,
      "automatonKills": 197024,
      "illuminateKills": 0,
      "bulletsFired": 1483584,
      "bulletsHit": 1467650,
      "timePlayed": 2583832,
      "deaths": 17282,
      "revives": 0,
      "friendlies": 654,
      "missionSuccessRate": 72,
      "accurracy": 98
    },
    {
      "planetIndex": 240,
      "missionsWon": 5324401,
      "missionsLost": 662394,
      "missionTime": 3866047213,
      "bugKills": 5338,
      "automatonKills": 306848621,
      "illuminateKills": 0,
      "bulletsFired": 2073376596,
      "bulletsHit": 1589700135,
      "timePlayed": 3866047213,
      "deaths": 15997752,
      "revives": 0,
      "friendlies": 1923069,
      "missionSuccessRate": 88,
      "accurracy": 76
    },
    {
      "planetIndex": 241,
      "missionsWon": 7507469,
      "missionsLost": 973299,
      "missionTime": 8340110274,
      "bugKills": 36907,
      "automatonKills": 657933588,
      "illuminateKills": 0,
      "bulletsFired": 4597275505,
      "bulletsHit": 4263622487,
      "timePlayed": 8340110274,
      "deaths": 31533848,
      "revives": 0,
      "friendlies": 3149138,
      "missionSuccessRate": 88,
      "accurracy": 92
    },
    {
      "planetIndex": 242,
      "missionsWon": 3131498,
      "missionsLost": 433938,
      "missionTime": 2744374803,
      "bugKills": 1510,
      "automatonKills": 200593446,
      "illuminateKills": 0,
      "bulletsFired": 1449126507,
      "bulletsHit": 1429322752,
      "timePlayed": 2744374803,
      "deaths": 14126318,
      "revives": 0,
      "friendlies": 1295260,
      "missionSuccessRate": 87,
      "accurracy": 98
    },
    {
      "planetIndex": 243,
      "missionsWon": 1871845,
      "missionsLost": 173253,
      "missionTime": 1473413556,
      "bugKills": 245,
      "automatonKills": 113152208,
      "illuminateKills": 0,
      "bulletsFired": 773277791,
      "bulletsHit": 796836706,
      "timePlayed": 1473413556,
      "deaths": 6726605,
      "revives": 0,
      "friendlies": 646813,
      "missionSuccessRate": 91,
      "accurracy": 100
    },
    {
      "planetIndex": 259,
      "missionsWon": 714127,
      "missionsLost": 71570,
      "missionTime": 559241241,
      "bugKills": 64675644,
      "automatonKills": 0,
      "illuminateKills": 0,
      "bulletsFired": 421306662,
      "bulletsHit": 484604368,
      "timePlayed": 559241241,
      "deaths": 2170015,
      "revives": 0,
      "friendlies": 321237,
      "missionSuccessRate": 90,
      "accurracy": 100
    },
    {
      "planetIndex": 260,
      "missionsWon": 27,
      "missionsLost": 0,
      "missionTime": 678,
      "bugKills": 0,
      "automatonKills": 0,
      "illuminateKills": 12,
      "bulletsFired": 498,
      "bulletsHit": 258,
      "timePlayed": 678,
      "deaths": 3,
      "revives": 0,
      "friendlies": 0,
      "missionSuccessRate": 100,
      "accurracy": 51
    }
  ]
}
