{
  "galaxy_stats": {
    "missionsWon": 75996169,
    "missionsLost": 7692736,
    "missionTime": 69236957240,
    "bugKills": 6656654572,
    "automatonKills": 1155863481,
    "illuminateKills": 28,
    "bulletsFired": 49463369838,
    "bulletsHit": 47100688619,
    "timePlayed": 69236957240,
    "deaths": 237930650,
    "revives": 2,
    "friendlies": 35832725,
    "missionSuccessRate": 90,
    "accurracy": 95
  },
  "planets_stats": [
    {
      "planetIndex": 0,
      "missionsWon": 35840,
      "missionsLost": 4331,
      "missionTime": 668,
      "bugKills": 0,
      "automatonKills": 0,
      "illuminateKills": 16,
      "bulletsFired": 464,
      "bulletsHit": 316,
      "timePlayed": 668,
      "deaths": 6,
      "revives": 0,
      "friendlies": 0,
      "missionSuccessRate": 89,
      "accurracy": 68
    },
    {
      "planetIndex": 34,
      "missionsWon": 6739275,
      "missionsLost": 833117,
      "missionTime": 5460212999,
      "bugKills": 605087714,
      "automatonKills": 107,
      "illuminateKills": 0,
      "bulletsFired": 3862661031,
      "bulletsHit": 4486988802,
      "timePlayed": 5460212999,
      "deaths": 22461424,
      "revives": 0,
      "friendlies": 3105143,
      "missionSuccessRate": 88,
      "accurracy": 100
    },
    {
      "planetIndex": 64,
      "missionsWon": 3309035,
      "missionsLost": 378412,
      "missionTime": 4028455188,
      "bugKills": 538086206,
      "automatonKills": 16718,
      "illuminateKills": 0,
      "bulletsFired": 3385936859,
      "bulletsHit": 3729813691,
      "timePlayed": 4028455188,
      "deaths": 14413860,
      "revives": 0,
      "friendlies": 2446976,
      "missionSuccessRate": 89,
      "accurracy": 100
    },
    {
      "planetIndex": 77,
      "missionsWon": 292,
      "missionsLost": 104,
      "missionTime": 172986,
      "bugKills": 20630,
      "automatonKills": 0,
      "illuminateKills": 0,
      "bulletsFired": 140773,
      "bulletsHit": 167620,
      "timePlayed": 172986,
      "deaths": 963,
      "revives": 0,
      "friendlies": 44,
      "missionSuccessRate": 73,
      "accurracy": 100
    },
    {
      "planetIndex": 78,
      "missionsWon": 8208771,
      "missionsLost": 760030,
      "missionTime": 6181646795,
      "bugKills": 743368875,
      "automatonKills": 195,
      "illuminateKills": 0,
      "bulletsFired": 4737553765,
      "bulletsHit": 5512063424,
      "timePlayed": 6181646795,
      "deaths": 22847883,
      "revives": 0,
      "friendlies": 3465180,
      "missionSuccessRate": 91,
      "accurracy": 100
    },
    {
      "planetIndex": 79,
      "missionsWon": 1346133,
      "missionsLost": 155845,
      "missionTime": 1000409192,
      "bugKills": 151329232,
      "automatonKills": 23,
      "illuminateKills": 0,
      "bulletsFired": 904990737,
      "bulletsHit": 1015504160,
      "timePlayed": 1000409192,
      "deaths": 3444383,
      "revives": 2,
      "friendlies": 679777,
      "missionSuccessRate": 89,
      "accurracy": 100
    },
    {
      "planetIndex": 80,
      "missionsWon": 2689,
      "missionsLost": 1132,
      "missionTime": 1720444,
      "bugKills": 207774,
      "automatonKills": 0,
      "illuminateKills": 0,
      "bulletsFired": 1307852,
      "bulletsHit": 1578435,
      "timePlayed": 1720444,
      "deaths": 10841,
      "revives": 0,
      "friendlies": 661,
      "missionSuccessRate": 70,
      "accurracy": 100
    },
    {
      "planetIndex": 107,
      "missionsWon": 8292,
      "missionsLost": 883,
      "missionTime": 7600659,
      "bugKills": 0,
      "automatonKills": 521505,
      "illuminateKills": 0,
      "bulletsFired": 3335863,
      "bulletsHit": 1884140,
      "timePlayed": 7600659,
      "deaths": 24912,
      "revives": 0,
      "friendlies": 2604,
      "missionSuccessRate": 90,
      "accurracy": 56
    },
    {
      "planetIndex": 125,
      "missionsWon": 5415000,
      "missionsLost": 342357,
      "missionTime": 6978640620,
      "bugKills": 808616957,
      "automatonKills": 93142,
      "illuminateKills": 0,
      "bulletsFired": 4997159850,
      "bulletsHit": 3082015923,
      "timePlayed": 6978640620,
      "deaths": 14384473,
      "revives": 0,
      "friendlies": 2383444,
      "missionSuccessRate": 94,
      "accurracy": 61
    },
    {
      "planetIndex": 126,
      "missionsWon": 9695236,
      "missionsLost": 623672,
      "missionTime": 11772025075,
      "bugKills": 1366628276,
      "automatonKills": 52464,
      "illuminateKills": 0,
      "bulletsFired": 8370563694,
      "bulletsHit": 5935823682,
      "timePlayed": 11772025075,
      "deaths": 28618994,
      "revives": 0,
      "friendlies": 5166119,
      "missionSuccessRate": 93,
      "accurracy": 70
    },
    {
      "planetIndex": 127,
      "missionsWon": 120419,
      "missionsLost": 26658,
      "missionTime": 38358092,
      "bugKills": 4778027,
      "automatonKills": 75,
      "illuminateKills": 0,
      "bulletsFired": 30569911,
      "bulletsHit": 28403806,
      "timePlayed": 38358092,
      "deaths": 167400,
      "revives": 0,
      "friendlies": 12338,
      "missionSuccessRate": 81,
      "accurracy": 92
    },
    {
      "planetIndex": 152,
      "missionsWon": 1210236,
      "missionsLost": 88807,
      "missionTime": 1374913638,
      "bugKills": 24614,
      "automatonKills": 95480567,
      "illuminateKills": 0,
      "bulletsFired": 728240221,
      "bulletsHit": 348703433,
      "timePlayed": 1374913638,
      "deaths": 3685907,
      "revives": 0,
      "friendlies": 434608,
      "missionSuccessRate": 93,
      "accurracy": 47
    },
    {
      "planetIndex": 153,
      "missionsWon": 3073676,
      "missionsLost": 389209,
      "missionTime": 2559488686,
      "bugKills": 462,
      "automatonKills": 194739722,
      "illuminateKills": 0,
      "bulletsFired": 1456132383,
      "bulletsHit": 1408754474,
      "timePlayed": 2559488686,
      "deaths": 12677469,
      "revives": 0,
      "friendlies": 1202288,
      "missionSuccessRate": 88,
      "accurracy": 96
    },
    {
      "planetIndex": 154,
      "missionsWon": 1369009,
      "missionsLost": 21730,
      "missionTime": 751218775,
      "bugKills": 1184,
      "automatonKills": 57842831,
      "illuminateKills": 0,
      "bulletsFired": 307175765,
      "bulletsHit": 160724407,
      "timePlayed": 751218775,
      "deaths": 2048263,
      "revives": 0,
      "friendlies": 358059,
      "missionSuccessRate": 98,
      "accurracy": 52
    },
    {
      "planetIndex": 155,
      "missionsWon": 4189,
      "missionsLost": 1000,
      "missionTime": 2748614,
      "bugKills": 0,
      "automatonKills": 246818,
      "illuminateKills": 0,
      "bulletsFired": 1571339,
      "bulletsHit": 1095809,
      "timePlayed": 2748614,
      "deaths": 12836,
      "revives": 0,
      "friendlies": 1345,
      "missionSuccessRate": 80,
      "accurracy": 69
    },
    {
      "planetIndex": 168,
      "missionsWon": 3143408,
      "missionsLost": 375819,
      "missionTime": 3688961692,
      "bugKills": 503325358,
      "automatonKills": 0,
      "illuminateKills": 0,
      "bulletsFired": 3023818542,
      "bulletsHit": 3523286245,
      "timePlayed": 3688961692,
      "deaths": 13505743,
      "revives": 0,
      "friendlies": 2379240,
      "missionSuccessRate": 89,
      "accurracy": 100
    },
    {
      "planetIndex": 169,
      "missionsWon": 9853007,
      "missionsLost": 1014698,
      "missionTime": 7534849480,
      "bugKills": 1018437849,
      "automatonKills": 408,
      "illuminateKills": 0,
      "bulletsFired": 6052972197,
      "bulletsHit": 6959063154,
      "timePlayed": 7534849480,
      "deaths": 27712913,
      "revives": 0,
      "friendlies": 4684985,
      "missionSuccessRate": 90,
      "accurracy": 100
    },
    {
      "planetIndex": 170,
      "missionsWon": 3888673,
      "missionsLost": 418161,
      "missionTime": 3036497031,
      "bugKills": 372517185,
      "automatonKills": 87,
      "illuminateKills": 0,
      "bulletsFired": 2423787641,
      "bulletsHit": 2824232710,
      "timePlayed": 3036497031,
      "deaths": 12135771,
      "revives": 0,
      "friendlies": 1735629,
      "missionSuccessRate": 90,
      "accurracy": 100
    },
    {
      "planetIndex": 196,
      "missionsWon": 2005237,
      "missionsLost": 316259,
      "missionTime": 1842804474,
      "bugKills": 290,
      "automatonKills": 131182165,
      "illuminateKills": 0,
      "bulletsFired": 984909136,
      "bulletsHit": 971303412,
      "timePlayed": 1842804474,
      "deaths": 10199154,
      "revives": 0,
      "friendlies": 959117,
      "missionSuccessRate": 86,
      "accurracy": 98
    },
    {
      "planetIndex": 197,
      "missionsWon": 2871503,
      "missionsLost": 269952,
      "missionTime": 2155193807,
      "bugKills": 24589,
      "automatonKills": 170064018,
      "illuminateKills": 0,
      "bulletsFired": 1162523111,
      "bulletsHit": 760464850,
      "timePlayed": 2155193807,
      "deaths": 7941801,
      "revives": 0,
      "friendlies": 1094279,
      "missionSuccessRate": 91,
      "accurracy": 65
    },
    {
      "planetIndex": 211,
      "missionsWon": 954790,
      "missionsLost": 96273,
      "missionTime": 758118169,
      "bugKills": 87404174,
      "automatonKills": 0,
      "illuminateKills": 0,
      "bulletsFired": 573921343,
      "bulletsHit": 665156030,
      "timePlayed": 758118169,
      "deaths": 3049594,
      "revives": 0,
      "friendlies": 447743,
      "missionSuccessRate": 90,
      "accurracy": 100
    },
    {
      "planetIndex": 212,
      "missionsWon": 4446514,
      "missionsLost": 466792,
      "missionTime": 3509101430,
      "bugKills": 438777591,
      "automatonKills": 26,
      "illuminateKills": 0,
      "bulletsFired": 2870499940,
      "bulletsHit": 3312204776,
      "timePlayed": 3509101430,
      "deaths": 13532512,
      "revives": 0,
      "friendlies": 2130368,
      "missionSuccessRate": 90,
      "accurracy": 100
    },
    {
      "planetIndex": 238,
      "missionsWon": 930487,
      "missionsLost": 62130,
      "missionTime": 1026228901,
      "bugKills": 19873,
      "automatonKills": 68486956,
      "illuminateKills": 0,
      "bulletsFired": 533773545,
      "bulletsHit": 253952782,
      "timePlayed": 1026228901,
      "deaths": 2868665,
      "revives": 0,
      "friendlies": 341239,
      "missionSuccessRate": 93,
      "accurracy": 47
    },
    {
      "planetIndex": 239,
      "missionsWon": 3677,
      "missionsLost": 1397,
      "missionTime": 2150530,
      "bugKills": 0,
      "automatonKills": 166281,
      "illuminateKills": 0,
      "bulletsFired": 1229500,
      "bulletsHit": 1220052,
      "timePlayed": 2150530,
      "deaths": 14741,
      "revives": 0,
      "friendlies": 556,
      "missionSuccessRate": 72,
      "accurracy": 99
    },
    {
      "planetIndex": 240,
      "missionsWon": 2895089,
      "missionsLost": 412090,
      "missionTime": 1873263549,
      "bugKills": 4625,
      "automatonKills": 160720498,
      "illuminateKills": 0,
      "bulletsFired": 991328729,
      "bulletsHit": 505907389,
      "timePlayed": 1873263549,
      "deaths": 6235086,
      "revives": 0,
      "friendlies": 1049348,
      "missionSuccessRate": 87,
      "accurracy": 51
    },
    {
      "planetIndex": 241,
      "missionsWon": 2663368,
      "missionsLost": 361034,
      "missionTime": 2033552041,
      "bugKills": 36119,
      "automatonKills": 170469691,
      "illuminateKills": 0,
      "bulletsFired": 1151504513,
      "bulletsHit": 720463275,
      "timePlayed": 2033552041,
      "deaths": 7758006,
      "revives": 0,
      "friendlies": 922888,
      "missionSuccessRate": 88,
      "accurracy": 62
    },
    {
      "planetIndex": 242,
      "missionsWon": 1597676,
      "missionsLost": 251654,
      "missionTime": 1452481720,
      "bugKills": 1451,
      "automatonKills": 105031865,
      "illuminateKills": 0,
      "bulletsFired": 779366498,
      "bulletsHit": 748056698,
      "timePlayed": 1452481720,
      "deaths": 7535435,
      "revives": 0,
      "friendlies": 733687,
      "missionSuccessRate": 86,
      "accurracy": 95
    },
    {
      "planetIndex": 243,
      "missionsWon": 10964,
      "missionsLost": 1081,
      "missionTime": 10690742,
      "bugKills": 0,
      "automatonKills": 747319,
      "illuminateKills": 0,
      "bulletsFired": 4412314,
      "bulletsHit": 2503888,
      "timePlayed": 10690742,
      "deaths": 32152,
      "revives": 0,
      "friendlies": 3671,
      "missionSuccessRate": 91,
      "accurracy": 56
    },
    {
      "planetIndex": 259,
      "missionsWon": 193657,
      "missionsLost": 18109,
      "missionTime": 155450565,
      "bugKills": 17955517,
      "automatonKills": 0,
      "illuminateKills": 0,
      "bulletsFired": 121981824,
      "bulletsHit": 139350978,
      "timePlayed": 155450565,
      "deaths": 609460,
      "revives": 0,
      "friendlies": 91389,
      "missionSuccessRate": 91,
      "accurracy": 100
    },
    {
      "planetIndex": 260,
      "missionsWon": 27,
      "missionsLost": 0,
      "missionTime": 678,
      "bugKills": 0,
      "automatonKills": 0,
      "illuminateKills": 12,
      "bulletsFired": 498,
      "bulletsHit": 258,
      "timePlayed": 678,
      "deaths": 3,
      "revives": 0,
      "friendlies": 0,
      "missionSuccessRate": 100,
      "accurracy": 51
    }
  ]
}
