{
  "galaxy_stats": {
    "missionsWon": 76130316,
    "missionsLost": 7709019,
    "missionTime": 69351917110,
    "bugKills": 6667101931,
    "automatonKills": 1158686106,
    "illuminateKills": 28,
    "bulletsFired": 49544934261,
    "bulletsHit": 47191199739,
    "timePlayed": 69351917110,
    "deaths": 238394960,
    "revives": 2,
    "friendlies": 35901373,
    "missionSuccessRate": 90,
    "accurracy": 95
  },
  "planets_stats": [
    {
      "planetIndex": 0,
      "missionsWon": 35840,
      "missionsLost": 4331,
      "missionTime": 668,
      "bugKills": 0,
      "automatonKills": 0,
      "illuminateKills": 16,
      "bulletsFired": 464,
      "bulletsHit": 316,
      "timePlayed": 668,
      "deaths": 6,
      "revives": 0,
      "friendlies": 0,
      "missionSuccessRate": 89,
      "accurracy": 68
    },
    {
      "planetIndex": 34,
      "missionsWon": 6739839,
      "missionsLost": 833359,
      "missionTime": 5460517928,
      "bugKills": 605128228,
      "automatonKills": 107,
      "illuminateKills": 0,
      "bulletsFired": 3862908014,
      "bulletsHit": 4487284618,
      "timePlayed": 5460517928,
      "deaths": 22463438,
      "revives": 0,
      "friendlies": 3105195,
      "missionSuccessRate": 88,
      "accurracy": 100
    },
    {
      "planetIndex": 64,
      "missionsWon": 3309058,
      "missionsLost": 378422,
      "missionTime": 4028472059,
      "bugKills": 538088131,
      "automatonKills": 16718,
      "illuminateKills": 0,
      "bulletsFired": 3385949634,
      "bulletsHit": 3729828581,
      "timePlayed": 4028472059,
      "deaths": 14413962,
      "revives": 0,
      "friendlies": 2446980,
      "missionSuccessRate": 89,
      "accurracy": 100
    },
    {
      "planetIndex": 77,
      "missionsWon": 292,
      "missionsLost": 104,
      "missionTime": 172986,
      "bugKills": 20630,
      "automatonKills": 0,
      "illuminateKills": 0,
      "bulletsFired": 140773,
      "bulletsHit": 167620,
      "timePlayed": 172986,
      "deaths": 963,
      "revives": 0,
      "friendlies": 44,
      "missionSuccessRate": 73,
      "accurracy": 100
    },
    {
      "planetIndex": 78,
      "missionsWon": 8209127,
      "missionsLost": 760135,
      "missionTime": 6181834873,
      "bugKills": 743393569,
      "automatonKills": 195,
      "illuminateKills": 0,
      "bulletsFired": 4737710516,
      "bulletsHit": 5512250736,
      "timePlayed": 6181834873,
      "deaths": 22848927,
      "revives": 0,
      "friendlies": 3465248,
      "missionSuccessRate": 91,
      "accurracy": 100
    },
    {
      "planetIndex": 79,
      "missionsWon": 1346138,
      "missionsLost": 155848,
      "missionTime": 1000412264,
      "bugKills": 151329573,
      "automatonKills": 23,
      "illuminateKills": 0,
      "bulletsFired": 904993843,
      "bulletsHit": 1015507618,
      "timePlayed": 1000412264,
      "deaths": 3444391,
      "revives": 2,
      "friendlies": 679777,
      "missionSuccessRate": 89,
      "accurracy": 100
    },
    {
      "planetIndex": 80,
      "missionsWon": 2691,
      "missionsLost": 1134,
      "missionTime": 1724055,
      "bugKills": 208108,
      "automatonKills": 0,
      "illuminateKills": 0,
      "bulletsFired": 1309828,
      "bulletsHit": 1580741,
      "timePlayed": 1724055,
      "deaths": 10851,
      "revives": 0,
      "friendlies": 661,
      "missionSuccessRate": 70,
      "accurracy": 100
    },
    {
      "planetIndex": 107,
      "missionsWon": 8293,
      "missionsLost": 883,
      "missionTime": 7601074,
      "bugKills": 0,
      "automatonKills": 521526,
      "illuminateKills": 0,
      "bulletsFired": 3335937,
      "bulletsHit": 1884184,
      "timePlayed": 7601074,
      "deaths": 24912,
      "revives": 0,
      "friendlies": 2604,
      "missionSuccessRate": 90,
      "accurracy": 56
    },
    {
      "planetIndex": 125,
      "missionsWon": 5415017,
      "missionsLost": 342360,
      "missionTime": 6978653650,
      "bugKills": 808618498,
      "automatonKills": 93142,
      "illuminateKills": 0,
      "bulletsFired": 4997169547,
      "bulletsHit": 3082028355,
      "timePlayed": 6978653650,
      "deaths": 14384536,
      "revives": 0,
      "friendlies": 2383455,
      "missionSuccessRate": 94,
      "accurracy": 61
    },
    {
      "planetIndex": 126,
      "missionsWon": 9695249,
      "missionsLost": 623676,
      "missionTime": 11772030108,
      "bugKills": 1366629071,
      "automatonKills": 52464,
      "illuminateKills": 0,
      "bulletsFired": 8370567551,
      "bulletsHit": 5935829090,
      "timePlayed": 11772030108,
      "deaths": 28619017,
      "revives": 0,
      "friendlies": 5166120,
      "missionSuccessRate": 93,
      "accurracy": 70
    },
    {
      "planetIndex": 127,
      "missionsWon": 120443,
      "missionsLost": 26665,
      "missionTime": 38373836,
      "bugKills": 4780069,
      "automatonKills": 75,
      "illuminateKills": 0,
      "bulletsFired": 30582330,
      "bulletsHit": 28419178,
      "timePlayed": 38373836,
      "deaths": 167465,
      "revives": 0,
      "friendlies": 12342,
      "missionSuccessRate": 81,
      "accurracy": 92
    },
    {
      "planetIndex": 152,
      "missionsWon": 1210236,
      "missionsLost": 88807,
      "missionTime": 1374913638,
      "bugKills": 24614,
      "automatonKills": 95480567,
      "illuminateKills": 0,
      "bulletsFired": 728240221,
      "bulletsHit": 348703433,
      "timePlayed": 1374913638,
      "deaths": 3685907,
      "revives": 0,
      "friendlies": 434608,
      "missionSuccessRate": 93,
      "accurracy": 47
    },
    {
      "planetIndex": 153,
      "missionsWon": 3073700,
      "missionsLost": 389221,
      "missionTime": 2559502346,
      "bugKills": 462,
      "automatonKills": 194740597,
      "illuminateKills": 0,
      "bulletsFired": 1456139865,
      "bulletsHit": 1408761508,
      "timePlayed": 2559502346,
      "deaths": 12677643,
      "revives": 0,
      "friendlies": 1202334,
      "missionSuccessRate": 88,
      "accurracy": 96
    },
    {
      "planetIndex": 154,
      "missionsWon": 1369010,
      "missionsLost": 21730,
      "missionTime": 751219063,
      "bugKills": 1184,
      "automatonKills": 57842849,
      "illuminateKills": 0,
      "bulletsFired": 307175879,
      "bulletsHit": 160724549,
      "timePlayed": 751219063,
      "deaths": 2048263,
      "revives": 0,
      "friendlies": 358059,
      "missionSuccessRate": 98,
      "accurracy": 52
    },
    {
      "planetIndex": 155,
      "missionsWon": 4191,
      "missionsLost": 1002,
      "missionTime": 2751959,
      "bugKills": 0,
      "automatonKills": 247072,
      "illuminateKills": 0,
      "bulletsFired": 1573879,
      "bulletsHit": 1097917,
      "timePlayed": 2751959,
      "deaths": 12860,
      "revives": 0,
      "friendlies": 1345,
      "missionSuccessRate": 80,
      "accurracy": 69
    },
    {
      "planetIndex": 168,
      "missionsWon": 3143433,
      "missionsLost": 375831,
      "missionTime": 3688983197,
      "bugKills": 503328304,
      "automatonKills": 0,
      "illuminateKills": 0,
      "bulletsFired": 3023832383,
      "bulletsHit": 3523302691,
      "timePlayed": 3688983197,
      "deaths": 13505857,
      "revives": 0,
      "friendlies": 2379254,
      "missionSuccessRate": 89,
      "accurracy": 100
    },
    {
      "planetIndex": 169,
      "missionsWon": 9853180,
      "missionsLost": 1014767,
      "missionTime": 7534957558,
      "bugKills": 1018455080,
      "automatonKills": 408,
      "illuminateKills": 0,
      "bulletsFired": 6053061322,
      "bulletsHit": 6959170158,
      "timePlayed": 7534957558,
      "deaths": 27713519,
      "revives": 0,
      "friendlies": 4685029,
      "missionSuccessRate": 90,
      "accurracy": 100
    },
    {
      "planetIndex": 170,
      "missionsWon": 3888790,
      "missionsLost": 418207,
      "missionTime": 3036568028,
      "bugKills": 372526985,
      "automatonKills": 87,
      "illuminateKills": 0,
      "bulletsFired": 2423851618,
      "bulletsHit": 2824308530,
      "timePlayed": 3036568028,
      "deaths": 12136232,
      "revives": 0,
      "friendlies": 1735648,
      "missionSuccessRate": 90,
      "accurracy": 100
    },
    {
      "planetIndex": 196,
      "missionsWon": 2010569,
      "missionsLost": 316973,
      "missionTime": 1847617982,
      "bugKills": 290,
      "automatonKills": 131533741,
      "illuminateKills": 0,
      "bulletsFired": 987351612,
      "bulletsHit": 973765416,
      "timePlayed": 1847617982,
      "deaths": 10224806,
      "revives": 0,
      "friendlies": 961506,
      "missionSuccessRate": 86,
      "accurracy": 98
    },
    {
      "planetIndex": 197,
      "missionsWon": 2903415,
      "missionsLost": 273445,
      "missionTime": 2182615661,
      "bugKills": 24589,
      "automatonKills": 172150606,
      "illuminateKills": 0,
      "bulletsFired": 1177042046,
      "bulletsHit": 775238548,
      "timePlayed": 2182615661,
      "deaths": 8074556,
      "revives": 0,
      "friendlies": 1106699,
      "missionSuccessRate": 91,
      "accurracy": 65
    },
    {
      "planetIndex": 211,
      "missionsWon": 972274,
      "missionsLost": 97965,
      "missionTime": 772353098,
      "bugKills": 88990715,
      "automatonKills": 0,
      "illuminateKills": 0,
      "bulletsFired": 583735712,
      "bulletsHit": 676553924,
      "timePlayed": 772353098,
      "deaths": 3105013,
      "revives": 0,
      "friendlies": 455845,
      "missionSuccessRate": 90,
      "accurracy": 100
    },
    {
      "planetIndex": 212,
      "missionsWon": 4508269,
      "missionsLost": 475097,
      "missionTime": 3563729340,
      "bugKills": 446602623,
      "automatonKills": 26,
      "illuminateKills": 0,
      "bulletsFired": 2916366149,
      "bulletsHit": 3364180354,
      "timePlayed": 3563729340,
      "deaths": 13723809,
      "revives": 0,
      "friendlies": 2169017,
      "missionSuccessRate": 90,
      "accurracy": 100
    },
    {
      "planetIndex": 238,
      "missionsWon": 930487,
      "missionsLost": 62130,
      "missionTime": 1026228901,
      "bugKills": 19873,
      "automatonKills": 68486956,
      "illuminateKills": 0,
      "bulletsFired": 533773545,
      "bulletsHit": 253952782,
      "timePlayed": 1026228901,
      "deaths": 2868665,
      "revives": 0,
      "friendlies": 341239,
      "missionSuccessRate": 93,
      "accurracy": 47
    },
    {
      "planetIndex": 239,
      "missionsWon": 3684,
      "missionsLost": 1400,
      "missionTime": 2153561,
      "bugKills": 0,
      "automatonKills": 166605,
      "illuminateKills": 0,
      "bulletsFired": 1232852,
      "bulletsHit": 1223320,
      "timePlayed": 2153561,
      "deaths": 14770,
      "revives": 0,
      "friendlies": 557,
      "missionSuccessRate": 72,
      "accurracy": 99
    },
    {
      "planetIndex": 240,
      "missionsWon": 2895089,
      "missionsLost": 412090,
      "missionTime": 1873263549,
      "bugKills": 4625,
      "automatonKills": 160720498,
      "illuminateKills": 0,
      "bulletsFired": 991328729,
      "bulletsHit": 505907389,
      "timePlayed": 1873263549,
      "deaths": 6235086,
      "revives": 0,
      "friendlies": 1049348,
      "missionSuccessRate": 87,
      "accurracy": 51
    },
    {
      "planetIndex": 241,
      "missionsWon": 2667034,
      "missionsLost": 361425,
      "missionTime": 2036237121,
      "bugKills": 36119,
      "automatonKills": 170681326,
      "illuminateKills": 0,
      "bulletsFired": 1152844432,
      "bulletsHit": 721789507,
      "timePlayed": 2036237121,
      "deaths": 7770676,
      "revives": 0,
      "friendlies": 923973,
      "missionSuccessRate": 88,
      "accurracy": 62
    },
    {
      "planetIndex": 242,
      "missionsWon": 1600440,
      "missionsLost": 252001,
      "missionTime": 1454780320,
      "bugKills": 1451,
      "automatonKills": 105203193,
      "illuminateKills": 0,
      "bulletsFired": 780505316,
      "bulletsHit": 749151928,
      "timePlayed": 1454780320,
      "deaths": 7547057,
      "revives": 0,
      "friendlies": 734783,
      "missionSuccessRate": 86,
      "accurracy": 95
    },
    {
      "planetIndex": 243,
      "missionsWon": 10966,
      "missionsLost": 1081,
      "missionTime": 10691149,
      "bugKills": 0,
      "automatonKills": 747325,
      "illuminateKills": 0,
      "bulletsFired": 4412359,
      "bulletsHit": 2503944,
      "timePlayed": 10691149,
      "deaths": 32153,
      "revives": 0,
      "friendlies": 3671,
      "missionSuccessRate": 91,
      "accurracy": 56
    },
    {
      "planetIndex": 259,
      "missionsWon": 203535,
      "missionsLost": 18930,
      "missionTime": 163556460,
      "bugKills": 18889140,
      "automatonKills": 0,
      "illuminateKills": 0,
      "bulletsFired": 127797407,
      "bulletsHit": 146082546,
      "timePlayed": 163556460,
      "deaths": 639617,
      "revives": 0,
      "friendlies": 96032,
      "missionSuccessRate": 91,
      "accurracy": 100
    },
    {
      "planetIndex": 260,
      "missionsWon": 27,
      "missionsLost": 0,
      "missionTime": 678,
      "bugKills": 0,
      "automatonKills": 0,
      "illuminateKills": 12,
      "bulletsFired": 498,
      "bulletsHit": 258,
      "timePlayed": 678,
      "deaths": 3,
      "revives": 0,
      "friendlies": 0,
      "missionSuccessRate": 100,
      "accurracy": 51
    }
  ]
}
