{
  "galaxy_stats": {
    "missionsWon": 78283072,
    "missionsLost": 7974295,
    "missionTime": 71129173286,
    "bugKills": 6811670746,
    "automatonKills": 1206168889,
    "illuminateKills": 28,
    "bulletsFired": 50824843643,
    "bulletsHit": 48606864271,
    "timePlayed": 71129173286,
    "deaths": 246032957,
    "revives": 2,
    "friendlies": 36936756,
    "missionSuccessRate": 90,
    "accurracy": 95
  },
  "planets_stats": [
    {
      "planetIndex": 0,
      "missionsWon": 35840,
      "missionsLost": 4331,
      "missionTime": 668,
      "bugKills": 0,
      "automatonKills": 0,
      "illuminateKills": 16,
      "bulletsFired": 464,
      "bulletsHit": 316,
      "timePlayed": 668,
      "deaths": 6,
      "revives": 0,
      "friendlies": 0,
      "missionSuccessRate": 89,
      "accurracy": 68
    },
    {
      "planetIndex": 34,
      "missionsWon": 6748862,
      "missionsLost": 837124,
      "missionTime": 5465704929,
      "bugKills": 605779486,
      "automatonKills": 107,
      "illuminateKills": 0,
      "bulletsFired": 3867106718,
      "bulletsHit": 4492315796,
      "timePlayed": 5465704929,
      "deaths": 22496833,
      "revives": 0,
      "friendlies": 3106914,
      "missionSuccessRate": 88,
      "accurracy": 100
    },
    {
      "planetIndex": 64,
      "missionsWon": 3309525,
      "missionsLost": 378628,
      "missionTime": 4028769275,
      "bugKills": 538121868,
      "automatonKills": 16718,
      "illuminateKills": 0,
      "bulletsFired": 3386188265,
      "bulletsHit": 3730115749,
      "timePlayed": 4028769275,
      "deaths": 14416024,
      "revives": 0,
      "friendlies": 2447091,
      "missionSuccessRate": 89,
      "accurracy": 100
    },
    {
      "planetIndex": 77,
      "missionsWon": 296,
      "missionsLost": 107,
      "missionTime": 174078,
      "bugKills": 20911,
      "automatonKills": 0,
      "illuminateKills": 0,
      "bulletsFired": 143258,
      "bulletsHit": 170464,
      "timePlayed": 174078,
      "deaths": 979,
      "revives": 0,
      "friendlies": 44,
      "missionSuccessRate": 73,
      "accurracy": 100
    },
    {
      "planetIndex": 78,
      "missionsWon": 8214108,
      "missionsLost": 761787,
      "missionTime": 6184531634,
      "bugKills": 743740275,
      "automatonKills": 195,
      "illuminateKills": 0,
      "bulletsFired": 4739930235,
      "bulletsHit": 5514901256,
      "timePlayed": 6184531634,
      "deaths": 22864812,
      "revives": 0,
      "friendlies": 3466315,
      "missionSuccessRate": 91,
      "accurracy": 100
    },
    {
      "planetIndex": 79,
      "missionsWon": 1346226,
      "missionsLost": 155886,
      "missionTime": 1000476158,
      "bugKills": 151339278,
      "automatonKills": 23,
      "illuminateKills": 0,
      "bulletsFired": 905052475,
      "bulletsHit": 1015576402,
      "timePlayed": 1000476158,
      "deaths": 3444715,
      "revives": 2,
      "friendlies": 679810,
      "missionSuccessRate": 89,
      "accurracy": 100
    },
    {
      "planetIndex": 80,
      "missionsWon": 2754,
      "missionsLost": 1161,
      "missionTime": 1757478,
      "bugKills": 211935,
      "automatonKills": 0,
      "illuminateKills": 0,
      "bulletsFired": 1338232,
      "bulletsHit": 1612535,
      "timePlayed": 1757478,
      "deaths": 11055,
      "revives": 0,
      "friendlies": 674,
      "missionSuccessRate": 70,
      "accurracy": 100
    },
    {
      "planetIndex": 107,
      "missionsWon": 8326,
      "missionsLost": 893,
      "missionTime": 7615911,
      "bugKills": 0,
      "automatonKills": 522909,
      "illuminateKills": 0,
      "bulletsFired": 3345421,
      "bulletsHit": 1892778,
      "timePlayed": 7615911,
      "deaths": 25024,
      "revives": 0,
      "friendlies": 2611,
      "missionSuccessRate": 90,
      "accurracy": 56
    },
    {
      "planetIndex": 125,
      "missionsWon": 5415391,
      "missionsLost": 342494,
      "missionTime": 6978876102,
      "bugKills": 808646420,
      "automatonKills": 93142,
      "illuminateKills": 0,
      "bulletsFired": 4997342583,
      "bulletsHit": 3082243709,
      "timePlayed": 6978876102,
      "deaths": 14386029,
      "revives": 0,
      "friendlies": 2383553,
      "missionSuccessRate": 94,
      "accurracy": 61
    },
    {
      "planetIndex": 126,
      "missionsWon": 9695609,
      "missionsLost": 623808,
      "missionTime": 11772237628,
      "bugKills": 1366654374,
      "automatonKills": 52464,
      "illuminateKills": 0,
      "bulletsFired": 8370737752,
      "bulletsHit": 5936033246,
      "timePlayed": 11772237628,
      "deaths": 28620258,
      "revives": 0,
      "friendlies": 5166204,
      "missionSuccessRate": 93,
      "accurracy": 70
    },
    {
      "planetIndex": 127,
      "missionsWon": 120842,
      "missionsLost": 26831,
      "missionTime": 38596940,
      "bugKills": 4808530,
      "automatonKills": 75,
      "illuminateKills": 0,
      "bulletsFired": 30753726,
      "bulletsHit": 28623782,
      "timePlayed": 38596940,
      "deaths": 168862,
      "revives": 0,
      "friendlies": 12437,
      "missionSuccessRate": 81,
      "accurracy": 93
    },
    {
      "planetIndex": 152,
      "missionsWon": 1210236,
      "missionsLost": 88807,
      "missionTime": 1374913638,
      "bugKills": 24614,
      "automatonKills": 95480567,
      "illuminateKills": 0,
      "bulletsFired": 728240221,
      "bulletsHit": 348703433,
      "timePlayed": 1374913638,
      "deaths": 3685907,
      "revives": 0,
      "friendlies": 434608,
      "missionSuccessRate": 93,
      "accurracy": 47
    },
    {
      "planetIndex": 153,
      "missionsWon": 3074305,
      "missionsLost": 389476,
      "missionTime": 2559901484,
      "bugKills": 462,
      "automatonKills": 194770915,
      "illuminateKills": 0,
      "bulletsFired": 1456390929,
      "bulletsHit": 1409006558,
      "timePlayed": 2559901484,
      "deaths": 12680292,
      "revives": 0,
      "friendlies": 1202460,
      "missionSuccessRate": 88,
      "accurracy": 96
    },
    {
      "planetIndex": 154,
      "missionsWon": 1369017,
      "missionsLost": 21734,
      "missionTime": 751226975,
      "bugKills": 1184,
      "automatonKills": 57843558,
      "illuminateKills": 0,
      "bulletsFired": 307181486,
      "bulletsHit": 160729973,
      "timePlayed": 751226975,
      "deaths": 2048332,
      "revives": 0,
      "friendlies": 358065,
      "missionSuccessRate": 98,
      "accurracy": 52
    },
    {
      "planetIndex": 155,
      "missionsWon": 4219,
      "missionsLost": 1029,
      "missionTime": 2784999,
      "bugKills": 0,
      "automatonKills": 249781,
      "illuminateKills": 0,
      "bulletsFired": 1595822,
      "bulletsHit": 1120333,
      "timePlayed": 2784999,
      "deaths": 13076,
      "revives": 0,
      "friendlies": 1354,
      "missionSuccessRate": 80,
      "accurracy": 70
    },
    {
      "planetIndex": 168,
      "missionsWon": 3144016,
      "missionsLost": 376115,
      "missionTime": 3689392251,
      "bugKills": 503377573,
      "automatonKills": 0,
      "illuminateKills": 0,
      "bulletsFired": 3024150442,
      "bulletsHit": 3523683273,
      "timePlayed": 3689392251,
      "deaths": 13508576,
      "revives": 0,
      "friendlies": 2379400,
      "missionSuccessRate": 89,
      "accurracy": 100
    },
    {
      "planetIndex": 169,
      "missionsWon": 9856071,
      "missionsLost": 1015991,
      "missionTime": 7536557514,
      "bugKills": 1018706441,
      "automatonKills": 408,
      "illuminateKills": 0,
      "bulletsFired": 6054413402,
      "bulletsHit": 6960759566,
      "timePlayed": 7536557514,
      "deaths": 27724291,
      "revives": 0,
      "friendlies": 4685792,
      "missionSuccessRate": 90,
      "accurracy": 100
    },
    {
      "planetIndex": 170,
      "missionsWon": 3890501,
      "missionsLost": 418761,
      "missionTime": 3037435008,
      "bugKills": 372639542,
      "automatonKills": 87,
      "illuminateKills": 0,
      "bulletsFired": 2424574542,
      "bulletsHit": 2825173746,
      "timePlayed": 3037435008,
      "deaths": 12141592,
      "revives": 0,
      "friendlies": 1735946,
      "missionSuccessRate": 90,
      "accurracy": 100
    },
    {
      "planetIndex": 196,
      "missionsWon": 2115063,
      "missionsLost": 332259,
      "missionTime": 1939525356,
      "bugKills": 290,
      "automatonKills": 138147480,
      "illuminateKills": 0,
      "bulletsFired": 1037204976,
      "bulletsHit": 1023730186,
      "timePlayed": 1939525356,
      "deaths": 10729281,
      "revives": 0,
      "friendlies": 1007905,
      "missionSuccessRate": 86,
      "accurracy": 98
    },
    {
      "planetIndex": 197,
      "missionsWon": 3468596,
      "missionsLost": 336599,
      "missionTime": 2652078954,
      "bugKills": 24727,
      "automatonKills": 207301809,
      "illuminateKills": 0,
      "bulletsFired": 1437584663,
      "bulletsHit": 1039098692,
      "timePlayed": 2652078954,
      "deaths": 10421537,
      "revives": 0,
      "friendlies": 1327586,
      "missionSuccessRate": 91,
      "accurracy": 72
    },
    {
      "planetIndex": 211,
      "missionsWon": 1321547,
      "missionsLost": 137557,
      "missionTime": 1058342655,
      "bugKills": 121125931,
      "automatonKills": 0,
      "illuminateKills": 0,
      "bulletsFired": 796379163,
      "bulletsHit": 922356092,
      "timePlayed": 1058342655,
      "deaths": 4285184,
      "revives": 0,
      "friendlies": 626403,
      "missionSuccessRate": 90,
      "accurracy": 100
    },
    {
      "planetIndex": 212,
      "missionsWon": 5452701,
      "missionsLost": 593437,
      "missionTime": 4348118618,
      "bugKills": 550954893,
      "automatonKills": 26,
      "illuminateKills": 0,
      "bulletsFired": 3578344695,
      "bulletsHit": 4117703096,
      "timePlayed": 4348118618,
      "deaths": 16652835,
      "revives": 0,
      "friendlies": 2693453,
      "missionSuccessRate": 90,
      "accurracy": 100
    },
    {
      "planetIndex": 238,
      "missionsWon": 930488,
      "missionsLost": 62131,
      "missionTime": 1026229560,
      "bugKills": 19873,
      "automatonKills": 68486990,
      "illuminateKills": 0,
      "bulletsFired": 533774216,
      "bulletsHit": 253953278,
      "timePlayed": 1026229560,
      "deaths": 2868671,
      "revives": 0,
      "friendlies": 341239,
      "missionSuccessRate": 93,
      "accurracy": 47
    },
    {
      "planetIndex": 239,
      "missionsWon": 3727,
      "missionsLost": 1425,
      "missionTime": 2184425,
      "bugKills": 0,
      "automatonKills": 169000,
      "illuminateKills": 0,
      "bulletsFired": 1249180,
      "bulletsHit": 1239598,
      "timePlayed": 2184425,
      "deaths": 14993,
      "revives": 0,
      "friendlies": 568,
      "missionSuccessRate": 72,
      "accurracy": 99
    },
    {
      "planetIndex": 240,
      "missionsWon": 2895093,
      "missionsLost": 412091,
      "missionTime": 1873265142,
      "bugKills": 4625,
      "automatonKills": 160720701,
      "illuminateKills": 0,
      "bulletsFired": 991329594,
      "bulletsHit": 505908199,
      "timePlayed": 1873265142,
      "deaths": 6235092,
      "revives": 0,
      "friendlies": 1049348,
      "missionSuccessRate": 87,
      "accurracy": 51
    },
    {
      "planetIndex": 241,
      "missionsWon": 2719136,
      "missionsLost": 367951,
      "missionTime": 2076520323,
      "bugKills": 36119,
      "automatonKills": 173751826,
      "illuminateKills": 0,
      "bulletsFired": 1175199634,
      "bulletsHit": 743829743,
      "timePlayed": 2076520323,
      "deaths": 7965894,
      "revives": 0,
      "friendlies": 941744,
      "missionSuccessRate": 88,
      "accurracy": 63
    },
    {
      "planetIndex": 242,
      "missionsWon": 1642823,
      "missionsLost": 258142,
      "missionTime": 1490491077,
      "bugKills": 1451,
      "automatonKills": 107811888,
      "illuminateKills": 0,
      "bulletsFired": 799425562,
      "bulletsHit": 767505756,
      "timePlayed": 1490491077,
      "deaths": 7729714,
      "revives": 0,
      "friendlies": 752701,
      "missionSuccessRate": 86,
      "accurracy": 96
    },
    {
      "planetIndex": 243,
      "missionsWon": 10980,
      "missionsLost": 1087,
      "missionTime": 10704176,
      "bugKills": 0,
      "automatonKills": 748220,
      "illuminateKills": 0,
      "bulletsFired": 4419376,
      "bulletsHit": 2510492,
      "timePlayed": 10704176,
      "deaths": 32255,
      "revives": 0,
      "friendlies": 3672,
      "missionSuccessRate": 90,
      "accurracy": 56
    },
    {
      "planetIndex": 259,
      "missionsWon": 276747,
      "missionsLost": 26653,
      "missionTime": 220759652,
      "bugKills": 25429944,
      "automatonKills": 0,
      "illuminateKills": 0,
      "bulletsFired": 171446113,
      "bulletsHit": 196365966,
      "timePlayed": 220759652,
      "deaths": 860835,
      "revives": 0,
      "friendlies": 128859,
      "missionSuccessRate": 91,
      "accurracy": 100
    },
    {
      "planetIndex": 260,
      "missionsWon": 27,
      "missionsLost": 0,
      "missionTime": 678,
      "bugKills": 0,
      "automatonKills": 0,
      "illuminateKills": 12,
      "bulletsFired": 498,
      "bulletsHit": 258,
      "timePlayed": 678,
      "deaths": 3,
      "revives": 0,
      "friendlies": 0,
      "missionSuccessRate": 100,
      "accurracy": 51
    }
  ]
}
