{
  "galaxy_stats": {
    "missionsWon": 78578714,
    "missionsLost": 8011712,
    "missionTime": 71361067362,
    "bugKills": 6828293892,
    "automatonKills": 1212859076,
    "illuminateKills": 28,
    "bulletsFired": 50983586611,
    "bulletsHit": 48783365349,
    "timePlayed": 71361067362,
    "deaths": 247100727,
    "revives": 2,
    "friendlies": 37060991,
    "missionSuccessRate": 90,
    "accurracy": 95
  },
  "planets_stats": [
    {
      "planetIndex": 0,
      "missionsWon": 35840,
      "missionsLost": 4331,
      "missionTime": 668,
      "bugKills": 0,
      "automatonKills": 0,
      "illuminateKills": 16,
      "bulletsFired": 464,
      "bulletsHit": 316,
      "timePlayed": 668,
      "deaths": 6,
      "revives": 0,
      "friendlies": 0,
      "missionSuccessRate": 89,
      "accurracy": 68
    },
    {
      "planetIndex": 34,
      "missionsWon": 6749740,
      "missionsLost": 837487,
      "missionTime": 5466245149,
      "bugKills": 605841825,
      "automatonKills": 107,
      "illuminateKills": 0,
      "bulletsFired": 3867512305,
      "bulletsHit": 4492789702,
      "timePlayed": 5466245149,
      "deaths": 22500207,
      "revives": 0,
      "friendlies": 3107158,
      "missionSuccessRate": 88,
      "accurracy": 100
    },
    {
      "planetIndex": 64,
      "missionsWon": 3309593,
      "missionsLost": 378655,
      "missionTime": 4028817096,
      "bugKills": 538127762,
      "automatonKills": 16718,
      "illuminateKills": 0,
      "bulletsFired": 3386224259,
      "bulletsHit": 3730160131,
      "timePlayed": 4028817096,
      "deaths": 14416349,
      "revives": 0,
      "friendlies": 2447124,
      "missionSuccessRate": 89,
      "accurracy": 100
    },
    {
      "planetIndex": 77,
      "missionsWon": 296,
      "missionsLost": 107,
      "missionTime": 174078,
      "bugKills": 20911,
      "automatonKills": 0,
      "illuminateKills": 0,
      "bulletsFired": 143258,
      "bulletsHit": 170464,
      "timePlayed": 174078,
      "deaths": 979,
      "revives": 0,
      "friendlies": 44,
      "missionSuccessRate": 73,
      "accurracy": 100
    },
    {
      "planetIndex": 78,
      "missionsWon": 8214582,
      "missionsLost": 761957,
      "missionTime": 6184799626,
      "bugKills": 743774600,
      "automatonKills": 195,
      "illuminateKills": 0,
      "bulletsFired": 4740146124,
      "bulletsHit": 5515161544,
      "timePlayed": 6184799626,
      "deaths": 22866479,
      "revives": 0,
      "friendlies": 3466423,
      "missionSuccessRate": 91,
      "accurracy": 100
    },
    {
      "planetIndex": 79,
      "missionsWon": 1346236,
      "missionsLost": 155893,
      "missionTime": 1000485499,
      "bugKills": 151340363,
      "automatonKills": 23,
      "illuminateKills": 0,
      "bulletsFired": 905059747,
      "bulletsHit": 1015584668,
      "timePlayed": 1000485499,
      "deaths": 3444780,
      "revives": 2,
      "friendlies": 679812,
      "missionSuccessRate": 89,
      "accurracy": 100
    },
    {
      "planetIndex": 80,
      "missionsWon": 2757,
      "missionsLost": 1162,
      "missionTime": 1759138,
      "bugKills": 212040,
      "automatonKills": 0,
      "illuminateKills": 0,
      "bulletsFired": 1339044,
      "bulletsHit": 1613517,
      "timePlayed": 1759138,
      "deaths": 11065,
      "revives": 0,
      "friendlies": 674,
      "missionSuccessRate": 70,
      "accurracy": 100
    },
    {
      "planetIndex": 107,
      "missionsWon": 8328,
      "missionsLost": 898,
      "missionTime": 7619180,
      "bugKills": 0,
      "automatonKills": 523146,
      "illuminateKills": 0,
      "bulletsFired": 3347352,
      "bulletsHit": 1894406,
      "timePlayed": 7619180,
      "deaths": 25053,
      "revives": 0,
      "friendlies": 2613,
      "missionSuccessRate": 90,
      "accurracy": 56
    },
    {
      "planetIndex": 125,
      "missionsWon": 5415430,
      "missionsLost": 342507,
      "missionTime": 6978896927,
      "bugKills": 808648908,
      "automatonKills": 93142,
      "illuminateKills": 0,
      "bulletsFired": 4997356683,
      "bulletsHit": 3082261163,
      "timePlayed": 6978896927,
      "deaths": 14386146,
      "revives": 0,
      "friendlies": 2383564,
      "missionSuccessRate": 94,
      "accurracy": 61
    },
    {
      "planetIndex": 126,
      "missionsWon": 9695674,
      "missionsLost": 623825,
      "missionTime": 11772276178,
      "bugKills": 1366658317,
      "automatonKills": 52464,
      "illuminateKills": 0,
      "bulletsFired": 8370766858,
      "bulletsHit": 5936067122,
      "timePlayed": 11772276178,
      "deaths": 28620464,
      "revives": 0,
      "friendlies": 5166226,
      "missionSuccessRate": 93,
      "accurracy": 70
    },
    {
      "planetIndex": 127,
      "missionsWon": 120904,
      "missionsLost": 26855,
      "missionTime": 38639954,
      "bugKills": 4813129,
      "automatonKills": 75,
      "illuminateKills": 0,
      "bulletsFired": 30784068,
      "bulletsHit": 28660026,
      "timePlayed": 38639954,
      "deaths": 169099,
      "revives": 0,
      "friendlies": 12452,
      "missionSuccessRate": 81,
      "accurracy": 93
    },
    {
      "planetIndex": 152,
      "missionsWon": 1210236,
      "missionsLost": 88807,
      "missionTime": 1374913638,
      "bugKills": 24614,
      "automatonKills": 95480567,
      "illuminateKills": 0,
      "bulletsFired": 728240221,
      "bulletsHit": 348703433,
      "timePlayed": 1374913638,
      "deaths": 3685907,
      "revives": 0,
      "friendlies": 434608,
      "missionSuccessRate": 93,
      "accurracy": 47
    },
    {
      "planetIndex": 153,
      "missionsWon": 3074423,
      "missionsLost": 389506,
      "missionTime": 2559959750,
      "bugKills": 462,
      "automatonKills": 194775361,
      "illuminateKills": 0,
      "bulletsFired": 1456426214,
      "bulletsHit": 1409041822,
      "timePlayed": 2559959750,
      "deaths": 12680635,
      "revives": 0,
      "friendlies": 1202478,
      "missionSuccessRate": 88,
      "accurracy": 96
    },
    {
      "planetIndex": 154,
      "missionsWon": 1369021,
      "missionsLost": 21734,
      "missionTime": 751230976,
      "bugKills": 1184,
      "automatonKills": 57843970,
      "illuminateKills": 0,
      "bulletsFired": 307183993,
      "bulletsHit": 160731761,
      "timePlayed": 751230976,
      "deaths": 2048345,
      "revives": 0,
      "friendlies": 358069,
      "missionSuccessRate": 98,
      "accurracy": 52
    },
    {
      "planetIndex": 155,
      "missionsWon": 4222,
      "missionsLost": 1032,
      "missionTime": 2789545,
      "bugKills": 0,
      "automatonKills": 250129,
      "illuminateKills": 0,
      "bulletsFired": 1598637,
      "bulletsHit": 1123291,
      "timePlayed": 2789545,
      "deaths": 13119,
      "revives": 0,
      "friendlies": 1355,
      "missionSuccessRate": 80,
      "accurracy": 70
    },
    {
      "planetIndex": 168,
      "missionsWon": 3144087,
      "missionsLost": 376140,
      "missionTime": 3689437001,
      "bugKills": 503382372,
      "automatonKills": 0,
      "illuminateKills": 0,
      "bulletsFired": 3024184605,
      "bulletsHit": 3523723109,
      "timePlayed": 3689437001,
      "deaths": 13508822,
      "revives": 0,
      "friendlies": 2379422,
      "missionSuccessRate": 89,
      "accurracy": 100
    },
    {
      "planetIndex": 169,
      "missionsWon": 9856472,
      "missionsLost": 1016128,
      "missionTime": 7536784084,
      "bugKills": 1018739890,
      "automatonKills": 408,
      "illuminateKills": 0,
      "bulletsFired": 6054603189,
      "bulletsHit": 6960984736,
      "timePlayed": 7536784084,
      "deaths": 27725764,
      "revives": 0,
      "friendlies": 4685912,
      "missionSuccessRate": 90,
      "accurracy": 100
    },
    {
      "planetIndex": 170,
      "missionsWon": 3890734,
      "missionsLost": 418820,
      "missionTime": 3037525858,
      "bugKills": 372651783,
      "automatonKills": 87,
      "illuminateKills": 0,
      "bulletsFired": 2424646038,
      "bulletsHit": 2825257280,
      "timePlayed": 3037525858,
      "deaths": 12142084,
      "revives": 0,
      "friendlies": 1735975,
      "missionSuccessRate": 90,
      "accurracy": 100
    },
    {
      "planetIndex": 196,
      "missionsWon": 2131573,
      "missionsLost": 334858,
      "missionTime": 1953478704,
      "bugKills": 290,
      "automatonKills": 139145341,
      "illuminateKills": 0,
      "bulletsFired": 1044571801,
      "bulletsHit": 1031067478,
      "timePlayed": 1953478704,
      "deaths": 10808076,
      "revives": 0,
      "friendlies": 1014890,
      "missionSuccessRate": 86,
      "accurracy": 98
    },
    {
      "planetIndex": 197,
      "missionsWon": 3551206,
      "missionsLost": 346655,
      "missionTime": 2717746215,
      "bugKills": 24727,
      "automatonKills": 212170960,
      "illuminateKills": 0,
      "bulletsFired": 1473460383,
      "bulletsHit": 1075322406,
      "timePlayed": 2717746215,
      "deaths": 10759246,
      "revives": 0,
      "friendlies": 1357832,
      "missionSuccessRate": 91,
      "accurracy": 72
    },
    {
      "planetIndex": 211,
      "missionsWon": 1384207,
      "missionsLost": 145578,
      "missionTime": 1107842314,
      "bugKills": 126769297,
      "automatonKills": 0,
      "illuminateKills": 0,
      "bulletsFired": 833534234,
      "bulletsHit": 965294830,
      "timePlayed": 1107842314,
      "deaths": 4501306,
      "revives": 0,
      "friendlies": 655476,
      "missionSuccessRate": 90,
      "accurracy": 100
    },
    {
      "planetIndex": 212,
      "missionsWon": 5569726,
      "missionsLost": 607138,
      "missionTime": 4438325414,
      "bugKills": 561739176,
      "automatonKills": 26,
      "illuminateKills": 0,
      "bulletsFired": 3649531258,
      "bulletsHit": 4200470828,
      "timePlayed": 4438325414,
      "deaths": 17021296,
      "revives": 0,
      "friendlies": 2745620,
      "missionSuccessRate": 90,
      "accurracy": 100
    },
    {
      "planetIndex": 238,
      "missionsWon": 930488,
      "missionsLost": 62131,
      "missionTime": 1026229578,
      "bugKills": 19873,
      "automatonKills": 68486990,
      "illuminateKills": 0,
      "bulletsFired": 533774216,
      "bulletsHit": 253953278,
      "timePlayed": 1026229578,
      "deaths": 2868671,
      "revives": 0,
      "friendlies": 341239,
      "missionSuccessRate": 93,
      "accurracy": 47
    },
    {
      "planetIndex": 239,
      "missionsWon": 3733,
      "missionsLost": 1430,
      "missionTime": 2189718,
      "bugKills": 0,
      "automatonKills": 169478,
      "illuminateKills": 0,
      "bulletsFired": 1252613,
      "bulletsHit": 1242540,
      "timePlayed": 2189718,
      "deaths": 15024,
      "revives": 0,
      "friendlies": 570,
      "missionSuccessRate": 72,
      "accurracy": 99
    },
    {
      "planetIndex": 240,
      "missionsWon": 2895093,
      "missionsLost": 412091,
      "missionTime": 1873265589,
      "bugKills": 4625,
      "automatonKills": 160720745,
      "illuminateKills": 0,
      "bulletsFired": 991330060,
      "bulletsHit": 505908611,
      "timePlayed": 1873265589,
      "deaths": 6235095,
      "revives": 0,
      "friendlies": 1049348,
      "missionSuccessRate": 87,
      "accurracy": 51
    },
    {
      "planetIndex": 241,
      "missionsWon": 2726679,
      "missionsLost": 369011,
      "missionTime": 2082236653,
      "bugKills": 36119,
      "automatonKills": 174184813,
      "illuminateKills": 0,
      "bulletsFired": 1178303142,
      "bulletsHit": 746892561,
      "timePlayed": 2082236653,
      "deaths": 7995021,
      "revives": 0,
      "friendlies": 944207,
      "missionSuccessRate": 88,
      "accurracy": 63
    },
    {
      "planetIndex": 242,
      "missionsWon": 1649256,
      "missionsLost": 259112,
      "missionTime": 1495710921,
      "bugKills": 1451,
      "automatonKills": 108196111,
      "illuminateKills": 0,
      "bulletsFired": 802211150,
      "bulletsHit": 770184152,
      "timePlayed": 1495710921,
      "deaths": 7757245,
      "revives": 0,
      "friendlies": 755292,
      "missionSuccessRate": 86,
      "accurracy": 96
    },
    {
      "planetIndex": 243,
      "missionsWon": 10981,
      "missionsLost": 1087,
      "missionTime": 10704176,
      "bugKills": 0,
      "automatonKills": 748220,
      "illuminateKills": 0,
      "bulletsFired": 4419376,
      "bulletsHit": 2510492,
      "timePlayed": 10704176,
      "deaths": 32255,
      "revives": 0,
      "friendlies": 3672,
      "missionSuccessRate": 90,
      "accurracy": 56
    },
    {
      "planetIndex": 259,
      "missionsWon": 277170,
      "missionsLost": 26777,
      "missionTime": 220983057,
      "bugKills": 25460174,
      "automatonKills": 0,
      "illuminateKills": 0,
      "bulletsFired": 171634821,
      "bulletsHit": 196589424,
      "timePlayed": 220983057,
      "deaths": 862186,
      "revives": 0,
      "friendlies": 128936,
      "missionSuccessRate": 91,
      "accurracy": 100
    },
    {
      "planetIndex": 260,
      "missionsWon": 27,
      "missionsLost": 0,
      "missionTime": 678,
      "bugKills": 0,
      "automatonKills": 0,
      "illuminateKills": 12,
      "bulletsFired": 498,
      "bulletsHit": 258,
      "timePlayed": 678,
      "deaths": 3,
      "revives": 0,
      "friendlies": 0,
      "missionSuccessRate": 100,
      "accurracy": 51
    }
  ]
}
